LICENSE.txt
README.md
pyproject.toml
setup.py
pysoar/Translocations.py
pysoar/__init__.py
pysoar/baseline.py
pysoar/event_detection.py
pysoar/find_peaks.py
pysoar/threshold.py
pysoar.egg-info/PKG-INFO
pysoar.egg-info/SOURCES.txt
pysoar.egg-info/dependency_links.txt
pysoar.egg-info/requires.txt
pysoar.egg-info/top_level.txt