Metadata-Version: 2.1
Name: pysoar
Version: 1.0.2
Summary: A data analysis tool for translocations in nanopores
Home-page: https://github.com/VladimirIvanovImperial/PySOAR.git
Author: Vladimir Ivanov
Author-email: vi4018@ic.ac.uk
License: MIT
Keywords: nanopore sensing,single molecule detection,signal processing,data analysis
Platform: UNKNOWN
Classifier: Development Status :: 5 - Production/Stable
Classifier: Intended Audience :: Science/Research
Classifier: License :: OSI Approved :: MIT License
Classifier: Programming Language :: Python :: 3
Classifier: Topic :: Scientific/Engineering :: Chemistry
Classifier: Topic :: Scientific/Engineering :: Physics
Classifier: Topic :: Scientific/Engineering
Classifier: Operating System :: OS Independent
License-File: LICENSE.txt
